pineapple/__init__.py
pineapple/authentication.py
pineapple/client.py
pineapple_store_connect-0.1.0.dist-info/LICENSE
pineapple_store_connect-0.1.0.dist-info/METADATA
pineapple_store_connect-0.1.0.dist-info/WHEEL
pineapple_store_connect-0.1.0.dist-info/top_level.txt
pineapple_store_connect-0.1.0.dist-info/RECORD
