Metadata-Version: 2.1
Name: pineapple-store-connect
Version: 0.1.0
Summary: Defines a python API to simplify connecting in App Store Connect.
Home-page: UNKNOWN
Author: Carlos Santoro
License: MIT
Platform: UNKNOWN
License-File: LICENSE
